CSTB_core/__init__.py
CSTB_core/engine/__init__.py
CSTB_core/engine/wordIntegerIndexing.py
CSTB_core/engine/word_detect.py
CSTB_core/utils/__init__.py
CSTB_core/utils/io.py
CSTB_core-0.1.dist-info/METADATA
CSTB_core-0.1.dist-info/WHEEL
CSTB_core-0.1.dist-info/top_level.txt
CSTB_core-0.1.dist-info/RECORD
