Metadata-Version: 2.1
Name: CSTB-core
Version: 0.1
Summary: Utility function for io and word searching and indexing
Home-page: https://github.com/MMSB-MOBI/CSTB_core
Author: Guillaume Launay, Cecile Hilpert
Author-email: pitooon@gmail.com, cecile.hilpert@gmail.com
License: BSD
Download-URL: https://github.com/MMSB-MOBI/CSTB_core/tarball/0.1
Keywords: crispr,webserver
Platform: UNKNOWN
Requires-Dist: docopt
Requires-Dist: biopython
